examples/__init__.py
kaggledatasets/__init__.py
kaggledatasets/version.py
kaggledatasets/core/__init__.py
kaggledatasets/core/config.py
kaggledatasets/core/dataset.py
kaggledatasets/core/downloader.py
kaggledatasets/core/fileops.py
kaggledatasets/core/utils.py
kaggledatasets/structured/__init__.py
kaggledatasets-0.0.1.dist-info/LICENSE
kaggledatasets-0.0.1.dist-info/METADATA
kaggledatasets-0.0.1.dist-info/WHEEL
kaggledatasets-0.0.1.dist-info/top_level.txt
kaggledatasets-0.0.1.dist-info/zip-safe
kaggledatasets-0.0.1.dist-info/RECORD
