Metadata-Version: 2.1
Name: kaggledatasets
Version: 0.0.1
Summary: Collection of Kaggle Datasets ready to use for Everyone
Home-page: https://github.com/kaggledatasets/kaggledatasets
Author: Omkar Prabhu
Author-email: prabhuomkar@yandex.com
License: Apache License 2.0
Platform: UNKNOWN
Classifier: Development Status :: 3 - Alpha
Classifier: Programming Language :: Python
Classifier: Programming Language :: Python :: 3.5
Classifier: Programming Language :: Python :: 3.6
Classifier: Programming Language :: Python :: 3.7
Classifier: License :: OSI Approved :: Apache Software License
Classifier: Operating System :: OS Independent
Requires-Dist: kaggle
Requires-Dist: pandas
Requires-Dist: numpy
